{"nodes": [{"id": "autotune", "label": "autotune.py", "file_type": "code", "source_file": "autotune.py", "source_location": "L1"}, {"id": "autotune_hardcoded_profile", "label": "_hardcoded_profile()", "file_type": "code", "source_file": "autotune.py", "source_location": "L121"}, {"id": "autotune_build_kernel_profile", "label": "build_kernel_profile()", "file_type": "code", "source_file": "autotune.py", "source_location": "L142"}, {"id": "autotune_compile_variant", "label": "compile_variant()", "file_type": "code", "source_file": "autotune.py", "source_location": "L169"}, {"id": "autotune_process_variant", "label": "process_variant()", "file_type": "code", "source_file": "autotune.py", "source_location": "L183"}, {"id": "autotune_autotune_kernel", "label": "autotune_kernel()", "file_type": "code", "source_file": "autotune.py", "source_location": "L265"}, {"id": "autotune_autotune_attention", "label": "autotune_attention()", "file_type": "code", "source_file": "autotune.py", "source_location": "L548"}, {"id": "autotune_main", "label": "main()", "file_type": "code", "source_file": "autotune.py", "source_location": "L678"}, {"id": "autotune_rationale_1", "label": "autotune.py \u2014 main entry point for the CUDA kernel auto-tuner.  Usage:     pytho", "file_type": "rationale", "source_file": "autotune.py", "source_location": "L1"}, {"id": "autotune_rationale_122", "label": "Kernel-name-based fallback used when source parsing fails.", "file_type": "rationale", "source_file": "autotune.py", "source_location": "L122"}, {"id": "autotune_rationale_143", "label": "Return a KernelProfile for the given kernel name.      When use_libclang=True (P", "file_type": "rationale", "source_file": "autotune.py", "source_location": "L143"}, {"id": "autotune_rationale_170", "label": "Compile a variant .cu with nvcc, capturing ptxas info.", "file_type": "rationale", "source_file": "autotune.py", "source_location": "L170"}, {"id": "autotune_rationale_196", "label": "Compile, (verify), benchmark, and analyse one kernel variant.      Returns a ful", "file_type": "rationale", "source_file": "autotune.py", "source_location": "L196"}, {"id": "autotune_rationale_280", "label": "Auto-tune one kernel: generate \u2192 verify \u2192 compile \u2192 benchmark \u2192 analyse.      Ar", "file_type": "rationale", "source_file": "autotune.py", "source_location": "L280"}, {"id": "autotune_rationale_552", "label": "Auto-tune all attention variants (Tiled + Flash \u00d7 seq_tile \u00d7 unroll).     Writes", "file_type": "rationale", "source_file": "autotune.py", "source_location": "L552"}], "edges": [{"source": "autotune", "target": "argparse", "relation": "imports", "confidence": "EXTRACTED", "source_file": "autotune.py", "source_location": "L29", "weight": 1.0}, {"source": "autotune", "target": "json", "relation": "imports", "confidence": "EXTRACTED", "source_file": "autotune.py", "source_location": "L30", "weight": 1.0}, {"source": "autotune", "target": "os", "relation": "imports", "confidence": "EXTRACTED", "source_file": "autotune.py", "source_location": "L31", "weight": 1.0}, {"source": "autotune", "target": "subprocess", "relation": "imports", "confidence": "EXTRACTED", "source_file": "autotune.py", "source_location": "L32", "weight": 1.0}, {"source": "autotune", "target": "sys", "relation": "imports", "confidence": "EXTRACTED", "source_file": "autotune.py", "source_location": "L33", "weight": 1.0}, {"source": "autotune", "target": "time", "relation": "imports", "confidence": "EXTRACTED", "source_file": "autotune.py", "source_location": "L34", "weight": 1.0}, {"source": "autotune", "target": "concurrent_futures", "relation": "imports_from", "confidence": "EXTRACTED", "source_file": "autotune.py", "source_location": "L35", "weight": 1.0}, {"source": "autotune", "target": "dataclasses", "relation": "imports_from", "confidence": "EXTRACTED", "source_file": "autotune.py", "source_location": "L36", "weight": 1.0}, {"source": "autotune", "target": "pathlib", "relation": "imports_from", "confidence": "EXTRACTED", "source_file": "autotune.py", "source_location": "L37", "weight": 1.0}, {"source": "autotune", "target": "typing", "relation": "imports_from", "confidence": "EXTRACTED", "source_file": "autotune.py", "source_location": "L38", "weight": 1.0}, {"source": "autotune", "target": "parser", "relation": "imports_from", "confidence": "EXTRACTED", "source_file": "autotune.py", "source_location": "L51", "weight": 1.0}, {"source": "autotune", "target": "generator", "relation": "imports_from", "confidence": "EXTRACTED", "source_file": "autotune.py", "source_location": "L53", "weight": 1.0}, {"source": "autotune", "target": "benchmark", "relation": "imports_from", "confidence": "EXTRACTED", "source_file": "autotune.py", "source_location": "L54", "weight": 1.0}, {"source": "autotune", "target": "roofline", "relation": "imports_from", "confidence": "EXTRACTED", "source_file": "autotune.py", "source_location": "L59", "weight": 1.0}, {"source": "autotune", "target": "occupancy", "relation": "imports_from", "confidence": "EXTRACTED", "source_file": "autotune.py", "source_location": "L60", "weight": 1.0}, {"source": "autotune", "target": "search", "relation": "imports_from", "confidence": "EXTRACTED", "source_file": "autotune.py", "source_location": "L61", "weight": 1.0}, {"source": "autotune", "target": "reporter", "relation": "imports_from", "confidence": "EXTRACTED", "source_file": "autotune.py", "source_location": "L62", "weight": 1.0}, {"source": "autotune", "target": "roofline", "relation": "imports_from", "confidence": "EXTRACTED", "source_file": "autotune.py", "source_location": "L68", "weight": 1.0}, {"source": "autotune", "target": "plots", "relation": "imports_from", "confidence": "EXTRACTED", "source_file": "autotune.py", "source_location": "L75", "weight": 1.0}, {"source": "autotune", "target": "verifier", "relation": "imports_from", "confidence": "EXTRACTED", "source_file": "autotune.py", "source_location": "L82", "weight": 1.0}, {"source": "autotune", "target": "ptx_analysis", "relation": "imports_from", "confidence": "EXTRACTED", "source_file": "autotune.py", "source_location": "L88", "weight": 1.0}, {"source": "autotune", "target": "cuda_graph", "relation": "imports_from", "confidence": "EXTRACTED", "source_file": "autotune.py", "source_location": "L94", "weight": 1.0}, {"source": "autotune", "target": "attention", "relation": "imports_from", "confidence": "EXTRACTED", "source_file": "autotune.py", "source_location": "L101", "weight": 1.0}, {"source": "autotune", "target": "autotune_hardcoded_profile", "relation": "contains", "confidence": "EXTRACTED", "source_file": "autotune.py", "source_location": "L121", "weight": 1.0}, {"source": "autotune", "target": "autotune_build_kernel_profile", "relation": "contains", "confidence": "EXTRACTED", "source_file": "autotune.py", "source_location": "L142", "weight": 1.0}, {"source": "autotune", "target": "autotune_compile_variant", "relation": "contains", "confidence": "EXTRACTED", "source_file": "autotune.py", "source_location": "L169", "weight": 1.0}, {"source": "autotune", "target": "autotune_process_variant", "relation": "contains", "confidence": "EXTRACTED", "source_file": "autotune.py", "source_location": "L183", "weight": 1.0}, {"source": "autotune", "target": "autotune_autotune_kernel", "relation": "contains", "confidence": "EXTRACTED", "source_file": "autotune.py", "source_location": "L265", "weight": 1.0}, {"source": "autotune", "target": "autotune_autotune_attention", "relation": "contains", "confidence": "EXTRACTED", "source_file": "autotune.py", "source_location": "L548", "weight": 1.0}, {"source": "autotune", "target": "autotune_main", "relation": "contains", "confidence": "EXTRACTED", "source_file": "autotune.py", "source_location": "L678", "weight": 1.0}, {"source": "autotune_build_kernel_profile", "target": "autotune_hardcoded_profile", "relation": "calls", "confidence": "INFERRED", "source_file": "autotune.py", "source_location": "L164", "weight": 0.8}, {"source": "autotune_process_variant", "target": "autotune_compile_variant", "relation": "calls", "confidence": "INFERRED", "source_file": "autotune.py", "source_location": "L204", "weight": 0.8}, {"source": "autotune_autotune_kernel", "target": "autotune_build_kernel_profile", "relation": "calls", "confidence": "INFERRED", "source_file": "autotune.py", "source_location": "L304", "weight": 0.8}, {"source": "autotune_autotune_attention", "target": "autotune_compile_variant", "relation": "calls", "confidence": "INFERRED", "source_file": "autotune.py", "source_location": "L584", "weight": 0.8}, {"source": "autotune_main", "target": "autotune_autotune_kernel", "relation": "calls", "confidence": "INFERRED", "source_file": "autotune.py", "source_location": "L959", "weight": 0.8}, {"source": "autotune_main", "target": "autotune_autotune_attention", "relation": "calls", "confidence": "INFERRED", "source_file": "autotune.py", "source_location": "L978", "weight": 0.8}, {"source": "autotune_rationale_1", "target": "autotune", "relation": "rationale_for", "confidence": "EXTRACTED", "source_file": "autotune.py", "source_location": "L1", "weight": 1.0}, {"source": "autotune_rationale_122", "target": "autotune_hardcoded_profile", "relation": "rationale_for", "confidence": "EXTRACTED", "source_file": "autotune.py", "source_location": "L122", "weight": 1.0}, {"source": "autotune_rationale_143", "target": "autotune_build_kernel_profile", "relation": "rationale_for", "confidence": "EXTRACTED", "source_file": "autotune.py", "source_location": "L143", "weight": 1.0}, {"source": "autotune_rationale_170", "target": "autotune_compile_variant", "relation": "rationale_for", "confidence": "EXTRACTED", "source_file": "autotune.py", "source_location": "L170", "weight": 1.0}, {"source": "autotune_rationale_196", "target": "autotune_process_variant", "relation": "rationale_for", "confidence": "EXTRACTED", "source_file": "autotune.py", "source_location": "L196", "weight": 1.0}, {"source": "autotune_rationale_280", "target": "autotune_autotune_kernel", "relation": "rationale_for", "confidence": "EXTRACTED", "source_file": "autotune.py", "source_location": "L280", "weight": 1.0}, {"source": "autotune_rationale_552", "target": "autotune_autotune_attention", "relation": "rationale_for", "confidence": "EXTRACTED", "source_file": "autotune.py", "source_location": "L552", "weight": 1.0}]}